inferlo/__init__.py
inferlo/base/__init__.py
inferlo/base/domain.py
inferlo/base/generic_graph_model.py
inferlo/base/graph_model.py
inferlo/base/inference_result.py
inferlo/base/test_graph_model.py
inferlo/base/variable.py
inferlo/base/factors/__init__.py
inferlo/base/factors/discrete_factor.py
inferlo/base/factors/discrete_factor_test.py
inferlo/base/factors/factor.py
inferlo/base/factors/function_factor.py
inferlo/base/factors/function_factor_test.py
inferlo/datasets/__init__.py
inferlo/datasets/dataset_loader.py
inferlo/datasets/dataset_loader_test.py
inferlo/datasets/uai_reader.py
inferlo/datasets/uai_writer.py
inferlo/forney/__init__.py
inferlo/forney/edge_elimination.py
inferlo/forney/edge_elimination_test.py
inferlo/forney/nfg_model.py
inferlo/forney/nfg_model_test.py
inferlo/forney/optimization/__init__.py
inferlo/forney/optimization/nfg_map_lp.py
inferlo/forney/optimization/nfg_map_lp_test.py
inferlo/gaussian/__init__.py
inferlo/gaussian/gaussian_model.py
inferlo/gaussian/gaussian_model_test.py
inferlo/gaussian/inference/__init__.py
inferlo/gaussian/inference/gaussian_belief_propagation.py
inferlo/generic/__init__.py
inferlo/generic/libdai_bp.py
inferlo/generic/libdai_bp_test.py
inferlo/generic/inference/__init__.py
inferlo/generic/inference/backward_bucket_elimination.py
inferlo/generic/inference/backward_bucket_elimination_test.py
inferlo/generic/inference/belief_propagation.py
inferlo/generic/inference/binary_tree_elimination.py
inferlo/generic/inference/bucket_elimination.py
inferlo/generic/inference/bucket_renormalization.py
inferlo/generic/inference/factor.py
inferlo/generic/inference/graphical_model.py
inferlo/generic/inference/inference.py
inferlo/generic/inference/inference_test.py
inferlo/generic/inference/mean_field.py
inferlo/generic/inference/mini_bucket_elimination.py
inferlo/generic/inference/weighted_mini_bucket_elimination.py
inferlo/graphs/__init__.py
inferlo/graphs/fast_dfs.py
inferlo/graphs/fast_dfs_test.py
inferlo-0.3.1.dist-info/LICENSE
inferlo-0.3.1.dist-info/METADATA
inferlo-0.3.1.dist-info/WHEEL
inferlo-0.3.1.dist-info/top_level.txt
inferlo-0.3.1.dist-info/RECORD
