Metadata-Version: 2.1
Name: inferlo
Version: 0.3.1
Summary: Inference, Learning & Optimization with Graphical Models
Home-page: https://github.com/InferLO/inferlo
Author: The InferLO Developers
License: Apache 2
Platform: UNKNOWN
Requires-Python: >=3.7
License-File: LICENSE
Requires-Dist: cvxpy (>=1.1.1)
Requires-Dist: networkx (>=2.5)
Requires-Dist: numba (>=0.52.0)
Requires-Dist: numpy (>=1.17)
Requires-Dist: scikit-learn (>=0.18)
Requires-Dist: scipy (>=1.4)
Requires-Dist: wget (>=3.0)
